{"r":{"e":{"s":{"e":{"r":{"v":{"a":{"t":{"i":{"o":{"n":{}}}},"s":{},"d":{"o":{}}},"e":{"d":{"e":{"e":{"p":{}}},"a":{}},"t":{"h":{"e":{},"i":{"s":{},"n":{"k":{}}}},"a":{"s":{"t":{"i":{"n":{"g":{}}}}}},"r":{"a":{"n":{"s":{"l":{"a":{"t":{"e":{"d":{}}}}}}}}}},"r":{"i":{"c":{"h":{}}}},"m":{"e":{"d":{"i":{"u":{"m":{"b":{"o":{"d":{"i":{"e":{"d":{}}}}}}}}}}},"i":{"g":{"n":{"o":{"n":{"s":{}}}}}}},"g":{"o":{"l":{"d":{}}}},"w":{"i":{"n":{"n":{"e":{"r":{}}},"e":{"a":{"l":{"i":{"g":{"n":{"s":{}}}}}}}}}},"e":{"t":{"h":{"i":{"s":{}},"e":{}}},"w":{"i":{"n":{"n":{"e":{"r":{}}}}}},"x":{"p":{"r":{"e":{"s":{"s":{"i":{"v":{"e":{}}}}}}}}}},"a":{"r":{"o":{"m":{"a":{"t":{"i":{"c":{}}}}}}},"l":{"i":{"s":{"o":{"n":{}}}}}},"b":{"i":{"g":{}}},"l":{"o":{"v":{"e":{"l":{"y":{}}}}}},"s":{"t":{"y":{"l":{"e":{}}}},"u":{"b":{"l":{"t":{"e":{}}}}}},"p":{"i":{"e":{"r":{"r":{"e":{}}}}}},"i":{"n":{}},"f":{"u":{"l":{"l":{"b":{"o":{"d":{"i":{"e":{"d":{}}}}}}}}}}}}},"m":{"b":{"l":{"e":{"s":{}},"i":{"n":{"g":{}}},"a":{"n":{"c":{"e":{}}}}}}},"a":{"r":{"c":{"h":{}}},"l":{"e":{"d":{}}}}},"t":{"i":{"n":{"g":{}},"t":{"u":{"t":{"a":{}}}}},"r":{"a":{"i":{"n":{"e":{"d":{}},"t":{},"i":{"n":{"g":{}}}}}},"i":{"c":{"t":{"e":{"d":{}}}}}},"a":{"u":{"r":{"a":{"n":{"t":{"s":{}}},"t":{"e":{"u":{"r":{}}}}}}},"t":{"e":{"d":{}}},"n":{"q":{"u":{"e":{"s":{}}}}}}},"o":{"n":{"a":{"n":{"t":{}},"t":{"i":{"n":{"g":{}}},"e":{}}}},"l":{"v":{"e":{"d":{},"s":{}},"i":{"n":{"g":{}}}},"u":{"t":{"e":{"l":{"y":{}}}}}},"u":{"n":{"d":{"i":{"n":{"g":{"l":{"y":{}}}}}}}}},"u":{"l":{"t":{"i":{"n":{"g":{}}},"e":{"d":{}},"s":{}}},"r":{"r":{"e":{"c":{"t":{"i":{"n":{"g":{}},"o":{"n":{}}},"e":{"d":{}}}}}},"f":{"a":{"c":{"e":{"s":{}}}}},"g":{"e":{"n":{"c":{"e":{}}}}}},"m":{"e":{}}},"a":{"l":{"s":{"o":{}},"t":{"e":{}}}},"i":{"s":{"t":{"a":{"n":{"t":{}}}}},"n":{"y":{"e":{"a":{"r":{"t":{"h":{"y":{}}}}}}},"o":{"u":{"s":{}}},"k":{"i":{"s":{"s":{"e":{"d":{}}}}}},"s":{}},"d":{"u":{"a":{"l":{}},"e":{}},"e":{"n":{"c":{"e":{}}}}}},"c":{"h":{"k":{"e":{}}},"u":{"e":{}}},"p":{"e":{"c":{"t":{"e":{"d":{}},"i":{"v":{"e":{"l":{"y":{"s":{"w":{"e":{"e":{"t":{"a":{"m":{"o":{"n":{"g":{}}}}}}}}}},"f":{"u":{"l":{"l":{"b":{"o":{"d":{"i":{"e":{"d":{}}}}}}}}}}}}}}},"s":{},"a":{"b":{"l":{"e":{}}}}}}},"i":{"t":{"e":{}},"d":{"e":{"m":{"e":{"d":{"e":{"v":{"i":{"l":{"l":{"e":{}}}}}}}}}}}},"l":{"e":{"n":{"d":{"e":{"n":{"t":{}}}}}}},"o":{"n":{"s":{"e":{},"i":{"b":{"l":{"e":{}},"i":{"l":{"i":{"t":{"y":{}}}}}}}},"d":{"i":{"n":{"g":{}}},"e":{"d":{}}}}}},"s":{"e":{"s":{}}},"v":{},"d":{"r":{"y":{}}}},"d":{"r":{"u":{"b":{"y":{}}}},"p":{"u":{"r":{"p":{"l":{"e":{"c":{"o":{"l":{"o":{"r":{"e":{"d":{}}}}}}}}}}}},"l":{"u":{"m":{}}}},"u":{"c":{"t":{"i":{"o":{"n":{"l":{"i":{"k":{"e":{}}}}}},"v":{"e":{}}}},"i":{"n":{"g":{}}},"e":{"d":{},"s":{}}}},"o":{"l":{"e":{"n":{"t":{}}}},"n":{"d":{"o":{}}},"m":{"a":{}}},"s":{"t":{"o":{"n":{"e":{}}}},"a":{"u":{"c":{"e":{"d":{}}}}}},"c":{"u":{"r":{"r":{"a":{"n":{"t":{"s":{}}}}}}},"h":{"e":{"r":{"r":{"y":{}}}}},"r":{"i":{"m":{"s":{"o":{"n":{}}}}}}},"d":{"i":{"s":{"h":{"p":{"u":{"r":{"p":{"l":{"e":{}}}}}}}}},"e":{"r":{},"n":{"e":{"d":{}}},"l":{"i":{"c":{"i":{"o":{"u":{"s":{}}}}}}}}},"b":{"e":{"r":{"r":{"y":{},"i":{"e":{"d":{}}}}}},"l":{"u":{"e":{}}},"r":{"o":{"w":{"n":{}},"o":{"k":{}}}}},"f":{"u":{"l":{"l":{"b":{"o":{"d":{"i":{"e":{"d":{}}}}}}}}},"r":{"u":{"i":{"t":{"y":{},"e":{"d":{}}}}}}},"t":{"o":{"n":{"e":{"d":{}}}},"i":{"n":{"g":{"e":{"d":{}}}}},"a":{"i":{"l":{}}}},"e":{"m":{"p":{"t":{"i":{"o":{"n":{}}}}}}},"w":{"i":{"n":{"e":{}}},"o":{"o":{"d":{}}}},"i":{"s":{"c":{"o":{"v":{"e":{"r":{"i":{"n":{"g":{}}},"e":{"d":{}}}}}}}}},"g":{"o":{"l":{"d":{}}}},"h":{"a":{"w":{"k":{}}}},"m":{"e":{"a":{"t":{}}}}},"a":{"c":{"h":{"i":{"n":{"g":{}}},"e":{"s":{},"d":{}}},"t":{"i":{"o":{"n":{"s":{}}}}}},"d":{"y":{"t":{"o":{"d":{"r":{"i":{"n":{"k":{}}}}}}},"i":{"n":{"g":{}}}},"e":{"r":{"s":{}}},"i":{"l":{"y":{}},"n":{"g":{}}},"s":{}},"p":{"p":{"e":{"a":{"r":{"s":{}}}}}},"l":{"i":{"z":{"e":{},"i":{"n":{"g":{}}}},"s":{"t":{"i":{"c":{"a":{"l":{"l":{"y":{}}}}}}},"e":{}},"t":{"y":{}}},"e":{"s":{}},"m":{}},"s":{"o":{"n":{"a":{"b":{"l":{"y":{"p":{"r":{"i":{"c":{"e":{"d":{}}}}}}},"e":{}}}},"s":{},"e":{"d":{}}}},"s":{"u":{"r":{"i":{"n":{"g":{"l":{"y":{}}}}}}}}},"u":{"d":{}},"f":{"f":{"i":{"r":{"m":{"i":{"n":{"g":{}}},"e":{"d":{}}}}}}},"r":{}},"g":{"i":{"o":{"n":{"m":{"e":{"d":{"i":{"u":{"m":{"b":{"o":{"d":{"i":{"e":{"d":{}}}}}}}}}}}},"a":{"l":{},"r":{"o":{"m":{"a":{"s":{}}}}}},"s":{},"t":{"h":{"i":{"s":{}},"e":{}}},"l":{"o":{"v":{"e":{"l":{"y":{}}}}}},"f":{"u":{"l":{"l":{"b":{"o":{"d":{"i":{"e":{"d":{}}}}}}}}}},"j":{"u":{"m":{"p":{}}}},"r":{"i":{"c":{"h":{}}}}}},"a":{"t":{"r":{"a":{"n":{"s":{"l":{"a":{"t":{"e":{"d":{}}}}}}}}}}},"n":{"a":{"t":{"o":{}}},"e":{}},"s":{"p":{"a":{"l":{"e":{}}}},"t":{"e":{"r":{}}}},"m":{"e":{"n":{}}}},"a":{"l":{"e":{"a":{"l":{"i":{}}}},"a":{},"i":{"a":{"l":{"i":{}}}}},"i":{"n":{"e":{"d":{}}}},"r":{"d":{"e":{"d":{}},"l":{"e":{"s":{"s":{}}}}}}},"r":{"e":{"t":{"t":{"a":{"b":{"l":{"y":{}}}},"i":{"n":{"g":{}}}}}}},"e":{"n":{"t":{}}},"n":{"a":{"r":{"d":{}}},"i":{"e":{"m":{"e":{"d":{"i":{"u":{"m":{"b":{"o":{"d":{"i":{"e":{"d":{}}}}}}}}}}}}}}},"u":{"l":{"a":{"r":{"i":{"t":{"y":{}}},"l":{"y":{}}},"t":{"i":{"o":{"n":{"s":{}}}}}}},"s":{"c":{"i":{}}},"a":{"l":{"a":{"r":{}}}},"e":{"n":{"g":{"o":{"s":{}}}}}},"g":{"i":{"n":{"a":{}},"a":{"n":{"o":{}}}}}},"p":{"l":{"a":{"y":{"s":{},"i":{"n":{"g":{}}},"e":{"d":{}}},"n":{"t":{"e":{"d":{}},"i":{"n":{"g":{}}}}},"c":{"e":{"d":{}},"i":{"n":{"g":{}}}}},"i":{"c":{"a":{"t":{"e":{}}}}},"e":{"t":{"e":{}}}},"r":{"e":{"s":{"e":{"n":{"t":{"a":{"t":{"i":{"o":{"n":{}},"v":{"e":{}}}}},"s":{},"e":{"d":{}},"i":{"n":{"g":{}}}}}}}},"i":{"s":{"e":{"d":{}}}},"o":{"d":{"u":{"c":{"t":{"i":{"o":{"n":{}}}},"e":{}}}}}},"e":{"a":{"t":{"s":{},"i":{"n":{"g":{}}},"e":{"d":{"l":{"y":{}}}}}}},"o":{"r":{"t":{"e":{"d":{"l":{"y":{}}}},"s":{}}},"l":{"h":{"o":{}}}},"u":{"t":{"a":{"t":{"i":{"o":{"n":{}}}}},"e":{"d":{}}},"b":{"l":{"i":{"c":{}}}}},"a":{"y":{},"s":{"s":{"e":{"d":{}}}},"i":{"d":{}}},"t":{"i":{"l":{"e":{"s":{"a":{"r":{"o":{"m":{"a":{"t":{"i":{"c":{}}}}}}}}}}}}}},"m":{"a":{"r":{"k":{"a":{"b":{"l":{"y":{},"e":{}}}},"s":{},"e":{"d":{}},"i":{"n":{"g":{}}}},"q":{"u":{"a":{"b":{"l":{"e":{}}}}}}},"i":{"n":{"s":{},"d":{"e":{"r":{}}},"i":{"n":{"g":{}}},"e":{"d":{}}}},"u":{"r":{"y":{}}}},"i":{"n":{"i":{"s":{"c":{"e":{"n":{"t":{}}}}}},"d":{"e":{"d":{},"r":{"s":{}}},"i":{"n":{"g":{}}},"s":{}}},"r":{"e":{"z":{}}},"a":{},"m":{"e":{"d":{"i":{"u":{"m":{"b":{"o":{"d":{"i":{"e":{"d":{}}}}}}}}}}}},"l":{"l":{"y":{}}}},"e":{"m":{"b":{"e":{"r":{}},"r":{"a":{"n":{"c":{"e":{"s":{}}}}}}}},"i":{}},"o":{"i":{"s":{"s":{"e":{"n":{"e":{"t":{}}}}}}},"t":{"e":{"l":{"y":{}}},"a":{}},"n":{"d":{"i":{"e":{"r":{"e":{}}}},"o":{},"e":{"t":{}}},"t":{}},"v":{"e":{"d":{}}},"l":{"i":{"n":{"o":{"s":{}}}}}},"y":{"t":{"h":{"e":{}}}},"n":{"a":{"n":{"t":{}}}},"r":{"e":{"z":{}}},"h":{"o":{"o":{"g":{"t":{"e":{}}}}}}},"b":{"e":{"n":{},"l":{},"c":{"c":{"a":{}}}},"o":{"u":{"r":{"g":{"e":{"o":{"n":{"m":{"u":{"r":{"e":{}}}}}}}}}}},"l":{"o":{"c":{"h":{"o":{"n":{}}}}}}},"f":{"r":{"e":{"s":{"h":{"i":{"n":{"g":{"l":{"y":{}}}}},"m":{"e":{"n":{"t":{}}}},"e":{"r":{},"d":{},"s":{}}},"c":{"o":{}}}},"i":{"g":{"e":{"r":{"a":{"t":{"e":{"d":{}},"o":{"r":{}}}}}}}},"a":{"i":{"n":{}}}},"i":{"n":{"e":{"m":{"e":{"n":{"t":{}}}},"d":{}}}},"o":{"s":{"c":{"o":{}},"k":{}}},"l":{"e":{"c":{"t":{"s":{},"e":{"d":{}},"i":{"n":{"g":{}},"o":{"n":{"s":{}}}}}},"t":{"s":{}}}},"e":{"r":{"s":{},"e":{"n":{"c":{"e":{},"i":{"a":{"f":{"u":{"l":{"l":{"b":{"o":{"d":{"i":{"e":{"d":{}}}}}}}}}}}}}}},"m":{"e":{"n":{"t":{"a":{"t":{"i":{"o":{"n":{}}}}}}}}},"r":{"e":{"d":{}},"i":{"n":{"g":{}}}},"t":{"s":{}},"n":{"c":{"i":{"a":{}}}}}},"u":{"s":{"e":{"s":{}}},"g":{"e":{}}}},"t":{"i":{"c":{"e":{"n":{"t":{},"c":{"e":{}}}}},"r":{"e":{"m":{"e":{"n":{"t":{}}}}},"o":{}}},"u":{"r":{"n":{"e":{"d":{}},"i":{"n":{"g":{}}},"s":{}}}},"r":{"o":{"s":{"p":{"e":{"c":{"t":{"i":{"v":{"e":{}}}}}}}}},"y":{},"a":{"i":{"n":{"e":{"d":{}}}}}},"a":{"s":{"t":{"e":{"d":{}},"i":{"n":{"g":{}}}}},"i":{"n":{"s":{},"i":{"n":{"g":{}}},"e":{"d":{}}},"l":{"e":{"d":{},"r":{}}}}},"o":{"u":{"r":{}},"r":{"n":{"o":{}}}},"s":{"i":{"n":{"a":{}}}}},"q":{"u":{"i":{"r":{"e":{"s":{},"d":{},"m":{"e":{"n":{"t":{}}}}},"i":{"n":{"g":{}}}},"s":{"i":{"t":{"e":{}}}},"n":{"g":{"u":{"a":{}}}}},"e":{"s":{"t":{"s":{}}},"n":{"a":{}}}}},"v":{"e":{"a":{"l":{"i":{"n":{"g":{}}},"s":{},"e":{"d":{}}}},"l":{"l":{"o":{}},"a":{"t":{"i":{"o":{"n":{}}}}},"s":{},"i":{"n":{"g":{}}}},"r":{"b":{"e":{"r":{"a":{"t":{"i":{"v":{"e":{}},"n":{"g":{}}},"e":{"s":{}}},"n":{"t":{}}}}}},"d":{"i":{"t":{"o":{}}},"y":{}},"e":{"d":{}},"t":{"e":{}},"i":{"e":{}}},"n":{"u":{"e":{"s":{}}},"g":{"e":{}}},"s":{"m":{"e":{"d":{"i":{"u":{"m":{"b":{"o":{"d":{"i":{"e":{"d":{}}}}}}}}}}}}}},"i":{"e":{"w":{"e":{"d":{"t":{"h":{"e":{}}}},"r":{"s":{}}},"m":{"e":{"d":{"i":{"u":{"m":{}}}}}},"s":{},"a":{},"i":{"n":{"g":{}}},"p":{"r":{"e":{"t":{"t":{"y":{}}}}}},"h":{"o":{"n":{"e":{"y":{"d":{"e":{"w":{}}}}}}}},"r":{"i":{"p":{"e":{}}}}}},"s":{"i":{"t":{"i":{"n":{"g":{}}},"e":{"d":{}}}},"e":{"d":{}},"t":{"a":{}}},"v":{"e":{"s":{},"d":{}},"a":{"l":{"i":{"s":{"t":{}}}}}},"t":{"a":{"l":{"i":{"z":{"i":{"n":{"g":{}}},"e":{"d":{}}}}}}}},"a":{"l":{"o":{}},"m":{"p":{}},"n":{"a":{}}},"o":{"l":{"v":{"e":{"s":{}},"i":{"n":{"g":{}}}},"u":{"t":{"i":{"o":{"n":{"i":{"z":{"e":{}}}}}}}}}},"v":{"e":{"d":{"u":{"p":{}}}}},"u":{"e":{}}},"c":{"o":{"m":{"m":{"e":{"n":{"d":{"e":{"d":{"r":{"e":{"f":{"i":{"n":{"e":{"d":{}}}}}}}}},"a":{"t":{"i":{"o":{"n":{}}}}}}}}}},"r":{"d":{"s":{}},"k":{"e":{"d":{}}},"b":{"a":{}}},"l":{"t":{"t":{"h":{"e":{},"i":{"s":{}}},"a":{"s":{"t":{"i":{"n":{"g":{}}}}}}},"f":{"u":{"l":{"l":{"b":{"o":{"d":{"i":{"e":{"d":{}}}}}}}}}},"s":{},"e":{},"a":{"n":{"t":{"m":{"a":{"n":{"i":{"p":{"u":{"l":{"a":{"n":{"t":{"r":{"i":{"c":{"h":{}}}}}}}}}}}}}}}}},"d":{"e":{"l":{"i":{"v":{"e":{"r":{"s":{}}}}}}}},"m":{"e":{"d":{"i":{"u":{"m":{"b":{"o":{"d":{"i":{"e":{"d":{}}}}}}}}}}}}},"l":{"e":{"c":{"t":{}}}}},"g":{"n":{"i":{"t":{"i":{"o":{"n":{"f":{"i":{"l":{"l":{"e":{"d":{}}}}}}}}}},"z":{"e":{"d":{},"s":{}},"a":{"b":{"l":{"e":{}}}}},"s":{"a":{"b":{"l":{"e":{},"y":{}}}},"e":{"d":{}}}}}},"n":{"c":{"i":{"l":{"e":{"s":{}}}}},"s":{"i":{"d":{"e":{"r":{"i":{"n":{"g":{}}}}}}}}},"u":{"r":{"s":{"e":{}}},"g":{"n":{"e":{"s":{}}}}}},"e":{"n":{"t":{"l":{"y":{}}}},"i":{"v":{"e":{"s":{},"d":{}},"i":{"n":{"g":{}}}}},"d":{"e":{"s":{}}},"s":{"s":{}},"p":{"t":{"a":{"c":{"l":{"e":{}}}},"i":{"o":{"n":{}}}}}},"a":{"n":{"a":{"t":{"i":{"s":{}}}},"t":{"i":{}}},"p":{"e":{"t":{}}},"l":{"l":{"s":{}}},"s":{}},"i":{"o":{"t":{"o":{"s":{}}}},"p":{"e":{},"i":{"e":{"n":{"t":{}}}}}},"t":{"o":{"r":{"y":{}}}},"l":{"a":{"s":{"s":{"i":{"f":{"i":{"c":{"a":{"t":{"i":{"o":{"n":{}}}}}}}}}}}}},"y":{"c":{"l":{"e":{"s":{}}}}},"u":{"r":{"r":{"i":{"n":{"g":{}}}}}},"k":{"o":{"n":{}}},"c":{"h":{"i":{"a":{}}}}},"w":{"a":{"r":{"d":{"i":{"n":{"g":{}}},"e":{"d":{}},"s":{}}},"t":{"c":{"h":{"i":{"n":{"g":{}}}}}}}},"l":{"e":{"n":{"t":{"l":{"e":{"s":{"s":{}}}}}},"a":{"s":{"e":{"s":{},"d":{}},"i":{"n":{"g":{}}}}},"v":{"a":{"n":{"t":{}}}}},"a":{"t":{"i":{"v":{"e":{"l":{"y":{}}}},"o":{"n":{"s":{"h":{"i":{"p":{}}}}}}},"e":{"d":{},"s":{}}},"x":{"e":{"d":{}},"i":{"n":{"g":{}}}},"u":{"n":{"c":{"h":{"e":{"d":{}}}}}},"y":{"s":{}}},"i":{"a":{"b":{"l":{"e":{}},"i":{"l":{"i":{"t":{"y":{}}}}}}},"e":{"s":{},"f":{}},"s":{"h":{"e":{"s":{}}}},"c":{},"g":{"i":{"o":{"n":{}}}}},"v":{"a":{"s":{}}},"u":{"c":{"t":{"a":{"n":{"t":{"l":{"y":{}}}}}}}},"y":{"i":{"n":{"g":{}}}}},"n":{"d":{"i":{"t":{"i":{"o":{"n":{"s":{}}}}}},"e":{"r":{"e":{"d":{}},"s":{}}},"o":{"l":{"a":{}}}},"c":{"o":{"n":{"t":{"r":{"e":{"s":{}}}}}}},"e":{"a":{},"t":{"h":{"e":{}},"a":{"n":{"g":{"y":{}}}}},"w":{"e":{"d":{}}},"f":{"u":{"l":{"l":{"b":{"o":{"d":{"i":{"e":{"d":{}}}}}}}}}},"r":{"o":{"b":{"e":{"r":{"t":{}}}}}}},"o":{"w":{"n":{"e":{"d":{}}}},"u":{},"v":{"a":{"t":{"e":{"d":{}}}}}},"w":{"o":{"o":{"d":{}}},"i":{"c":{"k":{}}}},"a":{"c":{"e":{"r":{}}},"t":{"o":{}},"u":{"d":{"a":{"t":{}}}},"i":{"s":{"s":{"a":{"n":{"c":{"e":{}}}}}}},"r":{"d":{"e":{"s":{}}}},"m":{"e":{"d":{}}}},"t":{"z":{},"a":{"s":{}}},"n":{"i":{"n":{"a":{}},"e":{"s":{}}}},"z":{"o":{}},"g":{"o":{},"u":{"i":{"n":{"g":{"a":{}}}}}},"i":{"e":{"r":{"i":{}}}}},"u":{"i":{"l":{"l":{"y":{}}}},"b":{"e":{"n":{"e":{"s":{"q":{"u":{"e":{}}}}}}}},"n":{"i":{"s":{}}},"s":{"a":{"b":{"l":{"e":{}}}}}},"e":{"m":{"e":{"r":{"g":{"e":{"s":{}}}}}},"k":{"s":{}},"f":{},"n":{"e":{"r":{"g":{"i":{"z":{"e":{"d":{}}}}}}}},"s":{"t":{"a":{"b":{"l":{"i":{"s":{"h":{"i":{"n":{"g":{}}}}}}}}}}},"l":{"s":{}},"v":{"a":{"l":{"u":{"a":{"t":{"i":{"o":{"n":{}}}}}}}}}},"i":{"l":{"l":{"y":{"s":{}}}},"s":{"h":{"u":{}}},"c":{"h":{"s":{"g":{"r":{"a":{"f":{}}}},"r":{"a":{"t":{}}}},"a":{"r":{"t":{"s":{"h":{"a":{"u":{"s":{"e":{"n":{}}}}}}}}}}}},"f":{},"n":{"h":{"a":{"r":{"t":{"s":{"h":{"a":{"u":{"s":{"e":{"n":{"s":{}}}}}}}}}}},"o":{"l":{"d":{}}}},"a":{"g":{"e":{"s":{}}}},"f":{"o":{"r":{"c":{"e":{"s":{},"d":{}}}}}},"s":{},"i":{"n":{"g":{"e":{"r":{}}}},"s":{"c":{"h":{}}}},"t":{"e":{"r":{"p":{"r":{"e":{"t":{"a":{"t":{"i":{"o":{"n":{}}}}}}}}}}}},"e":{"d":{}},"v":{"i":{"g":{"o":{"r":{"a":{"t":{"e":{"d":{}}}}}}}}}},"m":{"o":{"n":{"d":{}}},"a":{"g":{"i":{"n":{"e":{"d":{}}}}}},"e":{"r":{}}},"g":{"n":{"a":{"c":{}},"i":{"n":{"g":{}}},"s":{}}},"v":{"e":{"r":{}}}},"r":{"e":{"l":{"e":{"a":{"s":{"e":{"d":{}}}}}}},"o":{"l":{"l":{"e":{}}}}},"y":{"n":{"e":{"l":{"l":{"a":{}}},"k":{"e":{}}},"a":{"u":{"d":{}},"c":{}},"o":{"n":{},"l":{"d":{"s":{}}}}},"s":{"s":{"o":{"n":{}},"i":{"e":{"r":{}}}},"e":{"r":{}}},"b":{"i":{"e":{"r":{}}}},"e":{"s":{}}},"k":{"a":{}},"h":{"a":{"b":{"i":{"l":{"i":{"t":{"a":{"t":{"i":{"o":{"n":{}}}}}}}}}}}},"o":{"r":{"g":{"a":{"n":{"i":{"z":{"e":{"d":{}}}}}}}}}},"a":{"s":{"p":{"b":{"e":{"r":{"r":{"y":{"i":{"n":{"f":{"o":{"r":{"m":{"e":{"d":{}}}}}}}},"d":{"r":{"i":{"v":{"e":{"n":{}}}}}},"f":{"l":{"a":{"v":{"o":{"r":{"e":{"d":{}}}}}}},"i":{"l":{"l":{"e":{"d":{}}}}}},"b":{"l":{"a":{"c":{"k":{"b":{"e":{"r":{"r":{"y":{}}}}}}}}}}},"i":{"e":{"s":{"b":{"l":{"a":{"c":{"k":{"b":{"e":{"r":{"r":{"i":{"e":{"s":{}}}}}}}}}}}},"t":{"h":{"a":{"t":{}}}}}}}}}}}},"t":{"e":{"a":{"u":{}}}},"n":{},"o":{"n":{"c":{"o":{"r":{"t":{"e":{"s":{"e":{}}}}}}}}},"h":{"i":{}},"c":{"a":{"l":{}}},"a":{},"i":{"n":{"a":{}}},"b":{"e":{"r":{"r":{"y":{}}}}}},"c":{"y":{"b":{"r":{"i":{"g":{"h":{"t":{}}}}}},"c":{"r":{"i":{"s":{"p":{}}}}},"s":{"e":{"a":{"r":{"i":{"n":{"g":{}}}}}}}},"k":{"e":{"d":{}},"i":{"n":{"g":{"s":{}}}}},"e":{"s":{},"h":{"o":{"r":{"s":{"e":{}}}}}},"i":{"n":{"g":{},"e":{"s":{"s":{}}}},"e":{"r":{}},"m":{"o":{"s":{}}}},"o":{"n":{"t":{"e":{"u":{"r":{}}}}}},"h":{"a":{"e":{"l":{"r":{"a":{"y":{"m":{"a":{"g":{"c":{"o":{"m":{}}}}}}}}}}}}},"l":{"e":{"t":{"t":{"e":{}}}}}},"y":{"n":{"o":{"l":{"d":{"s":{}}}},"e":{"v":{"i":{"g":{"n":{"e":{"a":{"u":{}}}}}}},"r":{}},"a":{"u":{"d":{"s":{}}}}},"m":{"o":{"n":{"d":{"c":{"h":{"a":{"n":{"w":{"i":{"n":{"e":{"r":{"e":{"v":{"i":{"e":{"w":{"s":{"c":{"o":{"n":{"z":{}}}}}}}}}}}}}}}}}}},"l":{"a":{"f":{"o":{"n":{"t":{"a":{"s":{"t":{"i":{"n":{"g":{}}}}}}}}}}}},"s":{}}}}},"s":{},"a":{"s":{"l":{"i":{"k":{"e":{}}}}}}},"d":{"a":{"r":{}},"i":{"a":{"n":{"t":{},"c":{"e":{}}},"t":{"i":{"n":{"g":{}}},"e":{"s":{}}}},"c":{"i":{},"c":{"h":{"i":{"o":{}}}}},"o":{"c":{"a":{"n":{"a":{"d":{"a":{"c":{"a":{}}}}}}}}}},"d":{"a":{}},"f":{"o":{"r":{"d":{}}}},"o":{"u":{"x":{}}}},"r":{"e":{"l":{"y":{"s":{"e":{"e":{"n":{}}}}}},"r":{},"m":{"e":{"a":{"t":{"b":{"a":{"s":{"e":{"d":{}}}}}}}}}},"i":{"t":{"y":{}},"f":{"i":{"e":{"d":{}}}}},"a":{"n":{"g":{"i":{}}}},"o":{}},"n":{"g":{"e":{"s":{},"n":{},"r":{},"d":{}},"i":{"n":{"g":{}}},"a":{"s":{}}},"c":{"h":{"o":{},"s":{},"e":{"s":{}}},"i":{"o":{"l":{"i":{"k":{"e":{}}}}},"a":{"s":{}}},"o":{"u":{"r":{"t":{}}}}},"k":{"e":{"d":{}},"s":{},"i":{"n":{"g":{}}}},"d":{"y":{},"e":{"l":{"l":{}}},"a":{"l":{"l":{}}}},"v":{"i":{"e":{"r":{}}}},"i":{"e":{"r":{}}},"s":{"o":{"m":{}}}},"p":{"e":{"l":{},"t":{}},"h":{"a":{"l":{},"e":{"l":{"s":{"o":{"u":{"r":{"c":{"e":{"d":{}}}}}}}}}}},"i":{"d":{"f":{"i":{"r":{"e":{}}}},"l":{"y":{}}},"e":{"r":{"l":{"i":{"k":{"e":{}}}}}}},"s":{"o":{"d":{"i":{"a":{}}}},"a":{"n":{"i":{}}}},"p":{"o":{"r":{"t":{}}}},"a":{"u":{"r":{"a":{}}}}},"i":{"l":{"s":{}},"n":{"i":{"e":{"r":{}}},"s":{"t":{"o":{"r":{"m":{}}}}},"b":{"o":{"w":{}}},"y":{},"w":{"a":{"t":{"e":{"r":{}}}}},"o":{"l":{"d":{"i":{}}}},"f":{"a":{"l":{"l":{}}}},"e":{"r":{"o":{},"a":{}}}},"s":{"i":{"n":{"s":{},"g":{},"y":{"p":{"r":{"u":{"n":{"e":{}}}}}},"e":{"d":{"s":{"t":{"y":{"l":{"e":{}}}}}},"t":{"s":{}}},"o":{"u":{"s":{}}},"a":{"t":{"e":{}}}}},"e":{"d":{},"s":{}}},"a":{"n":{"o":{}}},"m":{"b":{"a":{"u":{"l":{"t":{}}}}},"a":{"t":{}},"o":{"n":{"d":{"a":{}}}}},"d":{}},"b":{"b":{"i":{"t":{},"o":{"s":{"o":{}}}}},"l":{"e":{"r":{"o":{"s":{}}}}},"a":{"u":{"d":{"p":{"r":{"o":{"m":{"i":{"s":{}}}}}}}},"j":{"a":{"t":{"h":{"e":{}}}}}},"o":{"s":{"o":{}},"u":{"r":{"c":{"e":{"f":{"u":{"l":{"l":{"b":{"o":{"d":{"i":{"e":{"d":{}}}}}}}}}}}}}}},"e":{"l":{"a":{"i":{"s":{}}}},"n":{"s":{"t":{"e":{"i":{"n":{}}}}}}},"i":{"g":{"a":{"t":{"o":{"f":{"u":{"l":{"l":{"b":{"o":{"d":{"i":{"e":{"d":{}}}}}}}}}}}}}}}},"t":{"i":{"n":{"g":{"s":{}}},"o":{"n":{},"s":{}}},"e":{"d":{},"a":{"u":{}}},"c":{"h":{"e":{"t":{"s":{},"i":{"n":{"g":{}}},"e":{"d":{}}}}}},"a":{"t":{"o":{"u":{"i":{"l":{"l":{"e":{"a":{}}}}}}}},"f":{"i":{"a":{}}}},"b":{"a":{"g":{}}},"t":{"i":{}},"z":{"e":{"n":{"b":{"e":{"r":{"g":{"e":{"r":{}}}}}}}}}},"u":{"z":{"a":{"n":{"s":{"g":{"l":{"a":{"s":{}}}},"e":{"g":{"l":{"a":{"f":{"u":{"l":{"l":{"b":{"o":{"d":{"i":{"e":{"d":{}}}}}}}}}},"w":{"h":{"a":{"t":{}}}},"m":{"e":{"d":{"i":{"u":{"m":{"b":{"o":{"d":{"i":{"e":{"d":{}}}}}}}}}}}},"t":{"h":{"e":{}}},"b":{"a":{"r":{"r":{"e":{"l":{}}}}}}}}}}},"g":{"a":{"s":{"s":{"i":{"e":{"s":{}}}}}}}}}},"p":{"o":{}},"t":{},"l":{"f":{"u":{"l":{"l":{"b":{"o":{"d":{"i":{"e":{"d":{}}}}}}}}}}},"n":{"a":{"t":{"e":{}}},"c":{"h":{"y":{}}}},"c":{"o":{"u":{"l":{"e":{}}}}},"s":{"c":{"h":{}}},"e":{"n":{}}},"o":{"u":{"l":{},"s":{"s":{"e":{"t":{}}}}}},"v":{"e":{"s":{"s":{"a":{}}},"n":{"s":{"w":{"o":{"o":{"d":{"s":{}}}}},"b":{"u":{"r":{"g":{}}}}},"t":{"o":{"s":{"m":{"e":{"d":{"i":{"u":{"m":{"b":{"o":{"d":{"i":{"e":{"d":{}}}}}}}}}}}}}},"s":{}}},"d":{},"l":{},"r":{"a":{}}},"i":{"n":{"e":{}},"s":{"h":{"i":{"n":{"g":{"l":{"y":{}}}}}}},"o":{"l":{"i":{"r":{"i":{"c":{"h":{}}}}}}},"e":{"r":{"e":{"s":{}}}}},"o":{"i":{"r":{"e":{}}}},"a":{"z":{"z":{"i":{}}}}},"m":{"o":{"s":{"c":{"e":{"t":{"o":{}}}},"p":{"a":{"u":{"l":{}}}}},"n":{"l":{"o":{"v":{"e":{"l":{"y":{}}}}}},"t":{"e":{"u":{}}}}},"n":{"i":{"s":{"t":{"a":{}}}}},"a":{"l":{},"t":{"o":{}},"n":{"e":{"g":{"r":{"a":{}}}}}},"p":{"s":{},"e":{"d":{}},"o":{"l":{"l":{"a":{}}}},"a":{"n":{"t":{}}}},"i":{"r":{"a":{"n":{"a":{}}},"e":{"z":{}}},"t":{"e":{"l":{"l":{"o":{}}}}}},"s":{"a":{"y":{}}},"e":{"y":{"s":{}}},"b":{"l":{"e":{"s":{}}},"u":{"n":{"c":{"t":{"i":{"o":{"u":{"s":{}}}}}}}}},"k":{"o":{"w":{"s":{"k":{"y":{}}}}}}},"g":{"u":{},"o":{"n":{},"s":{"e":{}},"u":{"t":{}}},"n":{"a":{"i":{"e":{}}},"e":{"d":{"d":{"a":{}}}}},"e":{}},"w":{"d":{},"b":{"o":{"n":{"e":{"d":{},"v":{"i":{"l":{"j":{"o":{"e":{"n":{}}}}}}}}}}}},"z":{"o":{"r":{"s":{}}},"e":{},"a":{}},"l":{"p":{"h":{}}},"f":{"f":{"a":{"e":{"l":{"e":{}}},"u":{"l":{"t":{}}}}},"a":{"e":{"l":{}}},"o":{"l":{"s":{"t":{"h":{"e":{}}}}}}},"h":{"o":{"u":{"l":{}}}},"j":{"o":{}}},"i":{"d":{"i":{"n":{"g":{}},"c":{"u":{"l":{"o":{"u":{"s":{"l":{"y":{}}}}}}}}},"g":{"e":{"p":{"o":{"i":{"n":{"t":{}}}}},"c":{"r":{"e":{"s":{"t":{}}}}}}},"e":{"s":{}},"d":{"l":{"i":{"n":{"g":{}}},"e":{"d":{}}},"o":{"c":{"h":{}}}},"o":{"l":{"f":{"o":{}}}}},"b":{"s":{"t":{"o":{"a":{"s":{"t":{"y":{}}}}}},"v":{"i":{"b":{"r":{"a":{"n":{"t":{}}}}}}},"a":{"n":{"o":{"t":{"h":{"e":{"r":{}}}}}}},"p":{"u":{"r":{"p":{"l":{"e":{"b":{"l":{"a":{"c":{"k":{}}}}}}}}}}},"f":{"u":{"l":{"l":{"b":{"o":{"d":{"i":{"e":{"d":{}}}}}}}}}},"m":{"e":{"d":{"i":{"u":{"m":{"b":{"o":{"d":{"i":{"e":{"d":{}}}}}}}}}}}}},"e":{"i":{"r":{"a":{}}},"r":{"a":{"s":{}},"o":{}},"a":{"u":{"v":{"i":{"l":{"l":{"e":{"s":{"h":{"o":{"w":{"i":{"n":{"g":{}}}}}}}}}}}},"p":{"i":{"e":{"r":{"r":{"e":{}}}}}}}},"y":{"e":{}}},"b":{"o":{"n":{"e":{"d":{}}}}},"i":{"e":{"r":{"e":{}}}},"o":{"l":{"l":{"a":{}}},"t":{"a":{}}},"f":{"u":{"l":{"l":{"b":{"o":{"d":{"i":{"e":{"d":{}}}}}}}}}}},"e":{"s":{"l":{"i":{"n":{"g":{"s":{},"o":{"p":{"e":{"n":{"s":{}}}}},"n":{"e":{"s":{"s":{}}}},"l":{"i":{"k":{"e":{}}}},"a":{"r":{"o":{"m":{"a":{"t":{"i":{"c":{}}}}}}}}}}}}},"u":{"s":{"s":{"e":{"c":{}}}},"f":{"l":{"a":{"g":{"e":{"t":{}}}}}},"t":{"o":{"r":{"t":{}}}}},"d":{"e":{"n":{"c":{"u":{"v":{"e":{"e":{}}}}}},"l":{}}},"l":{"s":{"i":{"n":{"g":{}}}},"i":{"n":{"g":{}}},"l":{"a":{}}},"f":{"l":{"e":{}}},"b":{"k":{"e":{}}}},"o":{"j":{"a":{"s":{},"n":{"a":{}}}},"r":{"r":{"e":{"t":{}}}},"n":{"d":{"o":{},"a":{}}},"l":{"i":{"t":{"e":{}}}},"t":{"o":{"u":{"s":{}}},"t":{"e":{}}},"s":{"f":{"u":{"l":{"l":{"b":{"o":{"d":{"i":{"e":{"d":{}}}}}}}}}}}},"p":{"e":{"l":{"y":{"f":{"r":{"u":{"i":{"t":{"e":{"d":{}}}}}}}}},"b":{"e":{"r":{"r":{"y":{}}}}},"n":{"e":{"s":{"s":{"m":{"e":{"e":{"t":{"s":{"s":{"t":{"r":{"u":{"c":{"t":{"u":{"r":{"e":{}}}}}}}}}}}}}}}},"d":{}},"i":{"n":{"g":{}}},"s":{}},"r":{},"s":{"t":{"y":{"l":{"e":{"d":{}}}}},"w":{"e":{"e":{"t":{"n":{"e":{"s":{"s":{}}}}}}}}},"f":{"r":{"u":{"i":{"t":{}}}}},"a":{"n":{"d":{"t":{"a":{"n":{"g":{"y":{}}}}}}}}},"a":{"s":{"s":{"o":{},"a":{}}},"n":{"i":{}},"r":{"o":{"s":{"s":{"o":{}}}}},"l":{"t":{"e":{}}}},"p":{"e":{"r":{}},"o":{"n":{}},"l":{"i":{"n":{"g":{}}},"e":{}},"i":{"n":{"g":{}}}},"o":{"l":{"l":{}}}},"c":{"h":{"l":{"y":{"f":{"r":{"u":{"i":{"t":{"e":{"d":{}}}}}}},"t":{"e":{"x":{"t":{"u":{"r":{"e":{"d":{}}}}}}}}},"o":{"v":{"e":{"l":{"y":{}}}},"t":{"s":{}},"o":{"k":{}}},"a":{"n":{"d":{}}},"i":{"g":{"h":{"t":{}}}},"e":{"m":{"o":{"n":{}}}}},"n":{"e":{"s":{"s":{}},"c":{"t":{"a":{"r":{"i":{"n":{"e":{}}}}}}},"w":{}},"o":{"w":{},"t":{"e":{"s":{}},"i":{"c":{"e":{"a":{"b":{"l":{"e":{}}}}}}}},"r":{"m":{"s":{}}}}},"b":{"i":{"g":{},"s":{"c":{"u":{"i":{"t":{"y":{}}}}}}},"o":{"l":{"d":{}}},"r":{"i":{"g":{"h":{"t":{}}},"l":{"l":{"i":{"a":{"n":{"t":{}}}}}}}},"u":{"r":{"s":{"t":{"i":{"n":{"g":{}}}}},"n":{"i":{"n":{"g":{}}}}},"t":{"t":{"e":{"r":{"e":{"d":{}}}}}}},"a":{"l":{"a":{"n":{"c":{"e":{"d":{}}}}}},"n":{"g":{},"a":{"n":{"a":{}}}}}},"t":{"h":{"i":{"s":{}},"e":{"r":{"e":{"s":{}}}},"r":{"o":{"u":{"g":{"h":{"o":{"u":{"t":{}}}}}}}}},"i":{"g":{"h":{"t":{"l":{"y":{}}}}}},"e":{"r":{}},"o":{"a":{"s":{"t":{"y":{}}}}},"r":{"a":{"n":{"s":{"l":{"a":{"t":{"e":{"d":{}}}}}}}},"o":{"p":{"i":{"c":{"a":{"l":{}}}}}}},"a":{"s":{"t":{"e":{"d":{}},"i":{"n":{"g":{}}}}}}},"e":{"b":{"o":{"u":{"r":{"g":{}}}}},"r":{"s":{"t":{"y":{"l":{"e":{"d":{}}}}},"a":{"u":{"c":{"e":{"d":{}}}}}}},"s":{"t":{}},"v":{"e":{"n":{}}},"m":{"e":{"r":{}}},"x":{"h":{"i":{"b":{"i":{"t":{"i":{"n":{"g":{}}}}}}}},"c":{"e":{"l":{"l":{"e":{"n":{"t":{}}}}}}}},"a":{"u":{"m":{"e":{}}}}},"a":{"r":{"d":{"s":{}},"o":{"m":{"a":{"s":{}}}}},"n":{"o":{"t":{"h":{"e":{"r":{}}}}}},"s":{},"t":{},"b":{"s":{"o":{"l":{"u":{"t":{"e":{"l":{"y":{}}}}}}}}},"p":{"p":{"l":{"e":{}}}},"d":{"e":{"l":{"s":{"h":{"e":{"i":{"m":{}}}}}}}},"l":{"t":{"h":{"o":{"u":{"g":{"h":{}}}}}},"l":{}}},"w":{"i":{"t":{"h":{}},"l":{"d":{"a":{"s":{"s":{}}}}}},"e":{"l":{"l":{"f":{"o":{"c":{"u":{"s":{"e":{"d":{}}}}}}}}}},"h":{"i":{"t":{"e":{}},"l":{"e":{}}},"a":{"t":{}}},"o":{"o":{"d":{}}}},"v":{"e":{"r":{"y":{}}},"i":{"s":{"c":{"o":{"u":{"s":{}}}}},"v":{"i":{"d":{}}}},"o":{"u":{"v":{"r":{"a":{"y":{}}}}}}},"r":{"i":{"c":{"h":{}},"p":{"e":{}}},"e":{"a":{"d":{"y":{}}},"s":{"t":{"r":{"a":{"i":{"n":{"e":{"d":{}}}}}}}},"d":{},"f":{"r":{"e":{"s":{"h":{"i":{"n":{"g":{}}}}}}}}},"o":{"u":{"n":{"d":{"e":{"d":{}}}}}}},"p":{"i":{"n":{"o":{"t":{}}}},"a":{"l":{"e":{}},"h":{"l":{"m":{"e":{"y":{"e":{"r":{"s":{}}}}}}}},"i":{"s":{"a":{"j":{"e":{}}}}}},"o":{"s":{"s":{"i":{"b":{"l":{"y":{}}}}}},"l":{"i":{"s":{"h":{"e":{"d":{}}}}}}},"e":{"a":{"r":{}},"r":{"f":{"e":{"c":{"t":{"l":{"y":{}}}}}}}},"u":{"r":{"p":{"l":{"e":{}}}}}},"o":{"p":{"e":{"n":{"i":{"n":{"g":{}}},"s":{}}}},"h":{},"n":{"e":{}},"l":{"d":{"v":{"i":{"n":{"e":{}}}}}},"u":{"t":{"s":{"t":{"a":{"n":{"d":{"i":{"n":{"g":{}}}}}}}}}},"f":{"f":{"e":{"r":{"s":{}}}}}},"m":{"a":{"d":{"e":{}}},"o":{"n":{"d":{}},"r":{"e":{}},"d":{"e":{"r":{"a":{"t":{"e":{}}}}}}},"e":{"d":{"i":{"u":{"m":{"b":{"o":{"d":{"i":{"e":{"d":{}}}}}}}}}}}},"j":{"a":{"d":{"o":{"t":{"s":{}}}}},"u":{"s":{"t":{}},"i":{"c":{"y":{}}}},"e":{"a":{"n":{"p":{"a":{"u":{"l":{}}}}}}}},"d":{"o":{"n":{"t":{}}},"i":{"s":{"t":{"i":{"n":{"c":{"t":{"i":{"v":{"e":{}}}}}}}}}},"e":{"l":{"i":{"v":{"e":{"r":{"s":{}}}},"c":{"i":{"o":{"u":{"s":{"l":{"y":{}}}}}}}}}},"a":{"v":{"i":{"d":{}}}},"r":{"i":{"n":{"k":{"i":{"n":{"g":{}}}}}}}},"s":{"o":{"f":{"t":{}},"u":{"r":{"c":{"e":{"d":{}}}}}},"e":{"r":{"v":{"e":{"d":{}}}},"e":{"i":{"n":{"g":{}}}},"t":{"s":{}}},"i":{"m":{"p":{"l":{"y":{}}}},"t":{"u":{"a":{"t":{"e":{"d":{}}}}}}},"m":{"o":{"k":{"y":{},"e":{}},"o":{"t":{"h":{}}}}},"a":{"n":{"t":{"a":{}}},"v":{"a":{"g":{"n":{"i":{"n":{}}}}}},"u":{"n":{"d":{"e":{"r":{"s":{}}}}}}},"t":{"a":{"r":{"t":{"s":{}}}},"e":{"p":{"s":{}}},"o":{"n":{"y":{}}},"r":{"a":{"w":{}}}},"u":{"b":{"t":{"l":{"e":{}}}}},"w":{"e":{"e":{"t":{}}}},"h":{"o":{"w":{"s":{}}}}},"i":{"n":{},"t":{"s":{}},"e":{},"v":{"e":{}}},"g":{"e":{"n":{"e":{"r":{"o":{"u":{"s":{}}}}},"t":{"l":{"y":{}}}}},"r":{"i":{"l":{"l":{"e":{"d":{}}}}},"a":{"c":{"e":{"f":{"u":{"l":{}}}}}},"e":{"e":{"n":{"t":{"i":{"n":{"g":{"e":{"d":{}}}}}}}}}},"o":{"r":{"g":{"e":{"o":{"u":{"s":{}}}}}},"l":{"d":{"e":{"n":{}}}},"o":{"d":{}}}},"c":{"i":{"t":{"r":{"u":{"s":{}}}}},"a":{"l":{"e":{"r":{"a":{"s":{}}}}},"r":{"a":{"m":{"e":{"l":{}}}}}},"r":{"i":{"s":{"p":{}}}},"o":{"m":{"p":{"l":{"e":{"x":{"i":{"t":{"y":{}}}}}},"r":{"i":{"s":{"e":{"d":{}}}}}}}},"l":{"a":{"s":{"s":{"y":{},"i":{"c":{}}}}},"o":{"s":{"s":{"o":{"n":{}}}}}},"h":{"a":{"t":{"e":{"a":{"u":{"n":{"e":{"u":{"f":{}}}}}}}},"r":{"d":{"o":{"n":{"n":{"a":{"y":{}}}}}}}},"e":{"n":{"i":{"n":{}}}}}},"f":{"r":{"o":{"m":{}},"e":{"s":{"h":{"l":{"y":{}}}}}},"e":{"a":{"t":{"u":{"r":{"e":{"s":{}}}}}}},"a":{"n":{"s":{}},"l":{"a":{"n":{"g":{"h":{"i":{"n":{"a":{}}}}}}}}},"u":{"l":{"l":{"b":{"o":{"d":{"i":{"e":{"d":{}}}}}}}}},"o":{"r":{"w":{"a":{"r":{"d":{}}}}}}},"y":{"o":{"u":{"t":{"h":{"f":{"u":{"l":{}}}}}}}},"k":{"i":{"t":{"c":{"h":{"e":{"n":{}}}}}}},"q":{"u":{"i":{"t":{"e":{}}}}},"h":{"e":{"d":{"o":{"n":{"i":{"s":{"t":{"i":{"c":{}}}}}}}},"r":{"e":{"s":{}}}},"a":{"y":{}}},"u":{"n":{"a":{"p":{"o":{"l":{"o":{"g":{"e":{"t":{"i":{"c":{"a":{"l":{"l":{"y":{}}}}}}}}}}}}}}}}},"k":{},"a":{"s":{"o":{"l":{"i":{}}}},"i":{"a":{"n":{"o":{}}}},"r":{"d":{},"i":{"c":{"o":{}}}},"u":{"d":{"e":{"t":{}}}},"g":{"n":{"o":{}}}},"e":{},"o":{"s":{"s":{"a":{}}},"t":{"t":{"a":{}}}},"c":{"a":{"r":{"d":{"o":{}}}},"i":{"t":{"e":{"l":{"l":{"i":{}}}}}}}},"n":{"g":{"s":{},"e":{"r":{}},"b":{"o":{"l":{"t":{}}}}},"d":{"s":{}},"a":{"l":{"d":{"i":{}}}},"c":{"n":{},"o":{"n":{}}}},"g":{"i":{"d":{"i":{"t":{"y":{}}}}},"o":{"d":{"e":{"i":{"r":{"a":{}}}}},"r":{"o":{"u":{"s":{"l":{"y":{}}}}}}},"n":{"a":{"n":{"a":{}}}},"h":{"t":{"s":{},"l":{"y":{}},"b":{"u":{"t":{}}}},"e":{"t":{"t":{"i":{}},"i":{}}}},"a":{"u":{"d":{}},"l":{}},"g":{"s":{}},"l":{"o":{"s":{}}}},"s":{"i":{"n":{"g":{}}},"e":{"r":{"v":{"a":{}}},"n":{},"s":{},"i":{"s":{}}},"o":{"t":{"t":{"o":{"w":{"h":{"i":{"t":{"e":{}}}}},"t":{"h":{"i":{"s":{}}}},"f":{"u":{"l":{"l":{"b":{"o":{"d":{"i":{"e":{"d":{}}}}}}}}}},"m":{"e":{"d":{"i":{"u":{"m":{"b":{"o":{"d":{"i":{"e":{"d":{}}}}}}}}}}}}}}}},"a":{"s":{"s":{"o":{}}}},"k":{"a":{"v":{"e":{"r":{"s":{"e":{}}}}}},"s":{},"t":{"a":{"k":{"i":{"n":{"g":{}}}}}}},"c":{"a":{"l":{}}}},"v":{"e":{"s":{"a":{"l":{"t":{"e":{"s":{}}}}}},"t":{"i":{"n":{"g":{}}},"t":{"e":{},"a":{},"i":{},"o":{}}},"r":{"s":{"i":{"d":{"e":{}}},"t":{"o":{"n":{"e":{}}}}},"a":{"s":{}},"v":{"i":{"e":{"w":{}}}},"m":{"e":{"d":{"i":{"u":{"m":{"b":{"o":{"d":{"i":{"e":{"d":{}}}}}}}}}}}},"p":{"o":{"i":{"n":{"t":{}}}}},"b":{"e":{"d":{}}},"i":{"n":{"a":{}}},"e":{}}},"i":{"e":{"r":{"e":{"t":{"h":{"i":{"s":{}}}},"f":{"u":{"l":{"l":{"b":{"o":{"d":{"i":{"e":{"d":{}}}}}}}}}},"s":{},"m":{"e":{"d":{"i":{"u":{"m":{"b":{"o":{"d":{"i":{"e":{"d":{}}}}}}}}}}}}},"a":{}}},"r":{"e":{}}},"a":{"l":{"l":{"o":{"n":{}}},"s":{},"t":{"a":{}},"i":{"n":{"g":{}}}},"g":{"e":{"s":{}}}},"r":{}},"f":{"f":{"a":{"u":{"l":{"t":{}}}},"s":{}},"l":{"e":{"m":{"a":{"n":{"s":{}}}}}}},"u":{"n":{"i":{"t":{"e":{}}}}},"a":{"z":{},"s":{},"l":{},"u":{"x":{}}},"t":{"a":{"s":{}},"c":{"h":{"i":{"e":{}}}},"u":{"a":{"l":{}}}},"m":{"u":{},"o":{"n":{}},"s":{},"a":{"u":{"r":{"e":{"s":{"q":{}}}}}}},"h":{"a":{"k":{"u":{}}}},"i":{"l":{"i":{}}},"l":{"e":{"y":{}},"l":{"y":{}}},"z":{"z":{"a":{"r":{"d":{"i":{}}}}},"l":{"i":{"n":{"g":{}}}}},"j":{"c":{"k":{"a":{"e":{"r":{"t":{}}}}}}},"q":{"u":{"e":{"w":{"i":{"h":{"r":{}}}}}}}},"o":{"b":{"e":{"r":{"t":{"s":{"o":{"n":{}}},"o":{}}}},"i":{"n":{"s":{"o":{"n":{}}},"o":{},"i":{"r":{"e":{}},"e":{"r":{"e":{"l":{"i":{"g":{"h":{"t":{}}}}}}}}}}},"u":{"s":{"t":{"l":{"y":{"s":{"t":{"y":{"l":{"e":{"d":{}}}}}}}},"n":{"e":{"s":{"s":{}}}},"o":{}}}},"y":{"n":{"s":{}}},"l":{"e":{"s":{}}},"r":{"e":{"d":{"o":{}}}},"b":{"i":{"n":{"g":{}}}},"o":{"r":{"e":{"d":{"o":{}}}}}},"u":{"n":{"d":{"e":{"d":{},"r":{}},"s":{},"i":{"n":{"g":{}}},"n":{"e":{"s":{"s":{}}}},"u":{"p":{}},"a":{"b":{"o":{"u":{"t":{"s":{}}}}}},"l":{"y":{}},"t":{"e":{"x":{"t":{"u":{"r":{"e":{"d":{}}}}}}}}}},"x":{},"l":{"e":{"t":{"t":{"e":{}}},"s":{}},"a":{"d":{"e":{"n":{}}}}},"s":{"s":{"a":{"n":{"n":{"e":{"s":{}}}}},"i":{"l":{"l":{"o":{"n":{"v":{"i":{"l":{"l":{"a":{"g":{"e":{"s":{}}}}}}}},"s":{}}}}}},"e":{"t":{"t":{"e":{}}},"a":{"u":{"s":{}}},"l":{"o":{"t":{}}}}},"t":{"i":{"t":{"s":{}}}},"i":{"l":{"l":{"o":{"n":{}}}},"n":{"g":{}}},"a":{"n":{"n":{"e":{}}}}},"g":{"e":{"f":{"o":{"r":{"t":{}}}},"s":{},"t":{}},"h":{"l":{"y":{}},"n":{"e":{"s":{"s":{}}}}}},"t":{"e":{"s":{}},"a":{"s":{}},"i":{"n":{"e":{"l":{"y":{}}}}}},"a":{"r":{"d":{"s":{}}}},"m":{"a":{"g":{"n":{"a":{"c":{}}}}}},"v":{"i":{"r":{"e":{}},"e":{"r":{"e":{"f":{"u":{"l":{"l":{"b":{"o":{"d":{"i":{"e":{"d":{}}}}}}}}}}}}}}},"d":{"i":{"l":{}}},"r":{"e":{}},"q":{"u":{"e":{"t":{"t":{"e":{}}}}}},"f":{"f":{"a":{"c":{"h":{}}}}}},"s":{"e":{"s":{"y":{"r":{"a":{"h":{}}}},"o":{"f":{"t":{}},"u":{"r":{"c":{"e":{"d":{}}}}}},"f":{"o":{"l":{"l":{"o":{"w":{}}}}}},"a":{"n":{"g":{"i":{"o":{"v":{"e":{"s":{"e":{}}}}}}}}},"i":{"t":{"u":{"a":{"t":{"e":{"d":{}}}}}}},"p":{"r":{"i":{"n":{"g":{}}}}}},"t":{"a":{"s":{"t":{"i":{"n":{"g":{}}}}}},"h":{"i":{"s":{}},"o":{"u":{"g":{"h":{}}}},"e":{}},"t":{"a":{}}},"l":{"i":{"g":{"h":{"t":{}}}},"l":{"a":{"s":{}}}},"m":{"a":{"r":{"y":{"s":{"e":{"a":{"s":{"o":{"n":{"e":{"d":{}}}}}}}},"c":{"r":{"u":{"s":{"t":{"e":{"d":{}}}}}}},"m":{"u":{"s":{"t":{"a":{"r":{"d":{}}}}}}}},"i":{"e":{"l":{"a":{"u":{"r":{"e":{}}}}}}}},"i":{"n":{"l":{"y":{}}}},"d":{"e":{}}},"e":{"d":{"i":{"u":{"m":{"b":{"o":{"d":{"i":{"e":{"d":{}}}}}}}}}}},"o":{"u":{"n":{"t":{}}}}},"e":{"a":{"s":{"y":{"g":{"o":{"i":{"n":{"g":{}}}}},"d":{"r":{"i":{"n":{"k":{"i":{"n":{"g":{}}}}}}}}}}},"r":{"n":{"e":{"s":{"t":{}}}}},"j":{"o":{"h":{"n":{}}}}},"n":{"b":{"l":{"u":{"m":{}}},"o":{"u":{"r":{"g":{}}}},"e":{"r":{"g":{}}}},"t":{"i":{"c":{"e":{"s":{}}}}},"g":{"a":{"r":{"t":{"e":{"n":{}}}}}},"o":{"t":{"a":{"b":{"l":{"y":{}}}}}}},"w":{"e":{},"o":{"o":{"d":{}}},"a":{"t":{"e":{"r":{}}}},"i":{"n":{"n":{"e":{"r":{}}}}}},"h":{"a":{"l":{"l":{}}},"e":{"r":{"e":{"s":{}}}},"i":{"p":{"s":{}}}},"r":{"i":{"c":{"h":{}},"p":{"e":{}}},"a":{"t":{"e":{"d":{}}}},"e":{"f":{"i":{"n":{"e":{"d":{}}}}}}},"d":{"a":{"l":{"e":{}}},"r":{"y":{}},"e":{"e":{"p":{}}},"o":{"m":{"a":{"i":{"n":{"e":{}}}}},"u":{"b":{"l":{"e":{}}}}}},"a":{"m":{"y":{"n":{"d":{"e":{"o":{"n":{}}}}}}}},"c":{"o":{"m":{"p":{"l":{"e":{"x":{}}}}}},"a":{"n":{"d":{"y":{"f":{"l":{"o":{"s":{"s":{}}}}}}}},"l":{"l":{"i":{"n":{"g":{}}}}}},"h":{"t":{"e":{"a":{"u":{}}}}}},"p":{"r":{"o":{"d":{"u":{"c":{"e":{"d":{}}}}}},"e":{"t":{"t":{"y":{"i":{"n":{"p":{"i":{"n":{"k":{}}}}}}}}}}},"e":{"t":{"a":{"l":{"r":{"e":{"d":{}}}}}}},"l":{"a":{"y":{"f":{"u":{"l":{}}}}}}},"b":{"u":{"s":{"h":{}}},"r":{"i":{"g":{"h":{"t":{}}}}},"a":{"r":{"e":{"l":{"y":{}}},"t":{"h":{"s":{}}}}}},"o":{"r":{"a":{"n":{"g":{"e":{"p":{"i":{"n":{"k":{}}}}}}}}}},"i":{"n":{"n":{"i":{"s":{"k":{"i":{"l":{"l":{"i":{"n":{}}}}}}}}}}},"v":{"i":{"n":{}},"e":{"r":{"y":{}}}},"f":{"a":{"u":{"s":{"t":{"i":{"n":{"o":{}}}}}}},"r":{"e":{"e":{}}}},"g":{"o":{"l":{"d":{}}}}},"s":{"o":{"m":{"e":{"d":{"i":{"u":{"m":{"b":{"o":{"d":{"i":{"e":{"d":{}}}}}}}}}}}},"b":{"a":{"s":{"t":{"a":{"r":{"d":{"o":{}}}}}}}},"a":{"r":{"o":{"m":{"a":{"t":{"i":{"c":{}}}}}}}},"f":{"u":{"l":{"l":{"b":{"o":{"d":{"i":{"e":{"d":{}}}}}}}}}},"s":{},"l":{"i":{"g":{"h":{"t":{}}}}}},"i":{"g":{"n":{"o":{"l":{"a":{}}}}}},"a":{},"e":{"n":{"d":{"a":{"l":{"e":{}}}}}},"j":{"b":{"a":{"s":{"s":{}}}}},"s":{"o":{}}},"a":{"s":{},"t":{"o":{}},"d":{"o":{}},"l":{"e":{"s":{}}},"z":{"z":{"a":{}}},"n":{"d":{"e":{"r":{"m":{"o":{"s":{"t":{}}}}}}}},"r":{"i":{"o":{}}}},"t":{"h":{"e":{}},"e":{"r":{}},"i":{"e":{}}},"y":{"h":{"u":{"e":{"d":{}}}}},"o":{"m":{"e":{"l":{}}}},"n":{"d":{"e":{"r":{}}}},"i":{"e":{"r":{}},"s":{}}},"g":{"e":{"r":{"s":{}}},"u":{"e":{}},"o":{"v":{"s":{}}},"n":{"e":{"t":{"s":{}}}},"g":{"i":{"o":{},"a":{"n":{"o":{}}}},"e":{"r":{"e":{}}}}},"a":{"s":{"t":{"e":{"d":{}},"s":{},"i":{"n":{"g":{}}},"t":{"h":{"e":{}}},"o":{"f":{"f":{"d":{"r":{"y":{}}}}}},"f":{"u":{"l":{"l":{"b":{"o":{"d":{"i":{"e":{"d":{}}}}}}}}}}}},"d":{"s":{"i":{"d":{"e":{}}}}},"m":{"i":{"n":{"g":{}}}},"i":{"x":{}},"g":{"n":{"a":{}}},"t":{}},"d":{"e":{"t":{}},"p":{"h":{"i":{"l":{"l":{"i":{"p":{"s":{"o":{"n":{"w":{"i":{"n":{"e":{"c":{"o":{"m":{}}}}}}}}}}}}}}}}},"n":{"e":{"y":{"s":{}}}},"r":{"i":{"g":{"u":{"e":{"z":{"a":{"r":{"o":{"m":{"a":{"t":{"i":{"c":{}}}}}}}}},"s":{}}},"o":{}}},"g":{"u":{"e":{"z":{}}}}},"i":{"t":{"i":{"s":{}}}},"a":{"s":{}},"d":{"i":{}},"o":{"l":{"f":{"o":{}}}}},"m":{"a":{"n":{"e":{"e":{"c":{"o":{"n":{"t":{"i":{}}}}},"s":{"t":{"v":{"i":{"v":{"a":{"n":{"t":{"p":{"a":{"l":{"e":{}}}}}}}}}}}}},"c":{"o":{"n":{"t":{"i":{}}}}},"i":{"r":{"a":{}}},"a":{"s":{"c":{"a":{"t":{"h":{"e":{}}}}}}},"s":{"t":{"v":{"i":{"v":{"a":{"n":{"t":{}}}}}}}}},"a":{},"i":{"e":{"r":{"a":{}}},"a":{"n":{}},"s":{},"n":{}},"s":{},"o":{},"d":{},"c":{"e":{}}},"i":{"n":{"s":{},"e":{}}},"g":{"n":{"a":{}}},"t":{"e":{}},"s":{}},"e":{"r":{"o":{}},"t":{},"o":{}},"n":{"e":{"a":{"s":{"c":{"a":{}}}}}},"p":{"i":{"c":{"o":{"l":{"l":{"o":{}}}}}}},"i":{"t":{"o":{"r":{"i":{"o":{}}}}},"g":{"b":{"e":{"r":{"g":{"t":{"r":{"a":{"n":{"s":{"l":{"a":{"t":{"e":{"d":{}}}}}}}}}}}}}}}},"b":{"o":{"n":{"e":{}}}}},"c":{"k":{"s":{"o":{"l":{"i":{"d":{}}}},"m":{"i":{"n":{"e":{"r":{"a":{"l":{"i":{"t":{"y":{}}}}}}}}}}},"y":{},"p":{"i":{"l":{"e":{}}}},"l":{"i":{"k":{"e":{}}}},"a":{"w":{"a":{"y":{}}}},"b":{"a":{"r":{"e":{}}}},"f":{"o":{"r":{"d":{}}},"a":{"l":{"l":{}}}},"i":{"n":{"g":{}}},"m":{"i":{"n":{"e":{"r":{"a":{"l":{}}}}}}},"w":{"a":{"y":{}}},"t":{"i":{"g":{"h":{"t":{}}}}}},"c":{"h":{"e":{"t":{"t":{"a":{}}}}},"o":{},"a":{"t":{"o":{}},"m":{"o":{"r":{"a":{}}}}}},"h":{"e":{"v":{"i":{"n":{"e":{"u":{"s":{"e":{}}}}},"l":{"l":{"e":{}}}}},"r":{},"b":{"i":{"n":{}}},"m":{"o":{"r":{"i":{"n":{}}}}},"c":{"o":{"l":{"o":{"m":{"b":{"e":{}}}}}}},"a":{"u":{"d":{"r":{"a":{"n":{}}}}}},"t":{"t":{"e":{}}},"u":{"s":{"e":{"s":{}}}},"s":{},"g":{"u":{"i":{"l":{"l":{"o":{"n":{}}}}}},"r":{"s":{},"e":{"s":{}}}},"f":{"o":{"n":{"d":{"u":{"g":{"a":{"r":{"d":{}}}}}}},"r":{"t":{"d":{"u":{"g":{"a":{"r":{"d":{}}}}}}}}}}}},"s":{},"p":{"i":{"n":{"e":{}}}},"e":{"p":{"i":{"n":{"e":{}}}}},"a":{"s":{},"l":{"i":{"r":{"e":{}},"e":{"r":{"e":{}}}}}},"i":{"m":{}},"o":{"u":{"l":{"e":{"s":{}}}}},"q":{"u":{"e":{"n":{"c":{"o":{"u":{"r":{"t":{}}}}}}}}}},"r":{"i":{"z":{}},"s":{"c":{"h":{"w":{"i":{"h":{"r":{}}}}}}}},"o":{"t":{"s":{"t":{"o":{"c":{"k":{}}}}},"v":{"e":{"g":{"e":{"t":{"a":{"b":{"l":{"e":{}}}}}},"g":{"i":{"e":{}}}}}},"y":{},"e":{"d":{}},"b":{"e":{"e":{"r":{}}}},"p":{"l":{"a":{"n":{"t":{"a":{"i":{"n":{}}}}}}}}},"f":{"t":{"o":{"p":{"s":{}}}}},"s":{"t":{"e":{"r":{}}}},"k":{"i":{"e":{"s":{}}}}},"t":{"h":{"s":{"c":{"h":{"i":{"l":{"d":{"s":{}}}}}}},"e":{"n":{"b":{"e":{"r":{"g":{}}}}}}},"i":{"e":{"r":{}},"s":{"s":{"e":{"r":{"i":{"e":{"m":{"e":{"d":{"i":{"u":{"m":{}}}}}}}}}}}}},"l":{"e":{"i":{"b":{"e":{"l":{}}}}},"a":{"c":{"k":{}}},"l":{"a":{"n":{"f":{"u":{"l":{"l":{"b":{"o":{"d":{"i":{"e":{"d":{}}}}}}}}}}}},"n":{}}},"e":{"b":{"o":{"e":{"u":{"f":{"b":{"l":{"a":{"c":{"k":{"i":{"s":{"h":{}}}}}}}},"d":{"a":{"r":{"k":{}}}}}}}}},"r":{},"n":{"b":{"e":{"r":{"g":{}}}}}},"a":{"t":{"i":{"n":{"g":{}}}},"l":{"i":{"a":{"n":{"o":{}}}}},"r":{"i":{}}},"t":{"l":{"a":{"n":{"d":{}}}},"g":{"e":{"n":{"p":{"e":{"r":{"s":{"i":{"a":{"n":{}}}}}}}}}},"i":{"e":{"r":{"s":{}}}}}},"n":{"c":{"a":{"o":{"f":{"u":{"l":{"l":{"b":{"o":{"d":{"i":{"e":{"d":{}}}}}}}}}}},"g":{"l":{"i":{"e":{"s":{}}}}}},"h":{"i":{}},"o":{"l":{"a":{"t":{"o":{}}}}},"e":{"r":{"e":{"t":{}}}}},"d":{"i":{"n":{"e":{"l":{"l":{"a":{}}}}}},"a":{},"e":{"s":{}}},"t":{"e":{"i":{"n":{}}}},"n":{},"a":{"l":{"d":{}},"n":{}}},"l":{"l":{"y":{"g":{"a":{"s":{"s":{"m":{"a":{"n":{"n":{"s":{}}}}}}}}}},"a":{"n":{"d":{"p":{"u":{"r":{"p":{"l":{"e":{}}}}}},"s":{},"m":{"a":{"i":{"l":{"l":{"e":{"t":{}}}}}}}}}},"s":{},"i":{"n":{"g":{}}},"e":{"d":{},"t":{}}},"e":{"s":{},"t":{}},"a":{"n":{"d":{}}},"f":{}},"w":{"a":{"n":{}},"s":{}},"y":{"a":{"l":{"e":{},"t":{"y":{}}}},"s":{},"t":{"h":{"v":{"e":{"n":{"i":{"n":{}}}}},"e":{"v":{"e":{"n":{"i":{"n":{"t":{"h":{"i":{"s":{}}}}}}}}}}}}},"e":{"d":{"e":{"r":{"e":{"r":{}}}},"a":{}},"s":{"m":{"o":{"u":{"n":{"t":{}}}}}},"r":{"o":{}}},"q":{"u":{"e":{"f":{"o":{"r":{"t":{}}}},"t":{"e":{},"a":{"i":{"l":{"l":{"a":{"d":{"e":{}}}}}}},"t":{"e":{}}},"s":{},"m":{"a":{"u":{"r":{"e":{}}}}},"b":{"r":{"u":{"n":{}}}}},"t":{"e":{}},"i":{"l":{"l":{"e":{}}}}}},"v":{"a":{"n":{"i":{}}},"e":{"r":{"e":{"t":{"o":{}}},"i":{"n":{"a":{}}}}}},"z":{"i":{"e":{"r":{}}}},"j":{"o":{},"a":{}},"p":{"e":{"s":{}}}},"h":{"n":{"e":{"v":{"i":{"l":{"l":{"a":{"g":{"e":{"s":{}}}}}}}},"s":{},"i":{"n":{"s":{"p":{"i":{"r":{"e":{"d":{}}}}}}}},"a":{},"f":{"u":{"l":{"l":{"b":{"o":{"d":{"i":{"e":{"d":{}}}}}}}}}}}},"o":{"n":{"e":{"g":{"o":{"l":{"d":{}}},"l":{"a":{"s":{"s":{"s":{"t":{"a":{"i":{"n":{"i":{"n":{"g":{}}}}}}}}}}}},"i":{"g":{"o":{"n":{"d":{"a":{"s":{}}}}}}}},"t":{"h":{"i":{"s":{}},"e":{},"o":{"r":{"o":{"u":{"g":{"h":{"l":{"y":{}}}}}}},"u":{"g":{"h":{}}}}},"o":{},"a":{"s":{"t":{"i":{"n":{"g":{}}},"e":{"d":{}}}},"v":{"e":{"l":{}}}},"r":{"a":{"n":{"s":{"l":{"a":{"t":{"e":{"d":{}}}}}}}}}},"f":{"u":{"l":{"l":{"b":{"o":{"d":{"i":{"e":{"d":{}}}}}}}}},"r":{"o":{"m":{}}},"a":{"n":{"t":{"a":{"s":{"t":{"i":{"c":{}}}}}}}},"i":{"r":{"m":{}}}},"v":{"i":{"l":{"l":{"a":{"g":{"e":{"s":{"s":{"w":{"e":{"e":{"t":{}}}},"e":{"r":{"i":{"o":{"u":{"s":{}}}}}},"i":{"g":{"n":{"a":{"r":{"g":{"u":{"e":{"s":{}}}}}}}}}},"w":{"i":{"n":{"n":{"e":{"r":{}}}}}},"a":{"r":{"o":{"m":{"a":{"s":{}}}}}},"t":{"h":{"e":{},"i":{"s":{}}},"o":{"f":{"f":{"e":{"e":{}}}}}},"v":{"i":{"n":{"s":{"o":{"b":{"r":{"e":{"s":{}}}}}}},"s":{"a":{"n":{}}}}},"f":{"u":{"l":{"l":{"b":{"o":{"d":{"i":{"e":{"d":{}}}}}}}}},"r":{"o":{"m":{}}}},"i":{"t":{},"n":{}},"g":{"o":{"l":{"d":{}}}},"m":{"e":{"d":{"i":{"u":{"m":{"b":{"o":{"d":{"i":{"e":{"d":{}}}}}}}}}}}},"p":{"e":{"r":{"h":{"a":{"p":{"s":{}}}}}},"l":{"a":{"n":{}}}},"b":{"u":{"i":{"l":{"t":{}}}}}}}}}}},"b":{"r":{"a":{"n":{"t":{}}}}},"n":{},"v":{"i":{"d":{}}}},"e":{"r":{"y":{}}}},"a":{"f":{"t":{"e":{"r":{}}}},"n":{"o":{"t":{"h":{"e":{"r":{}}}}}},"r":{"o":{"m":{"a":{"t":{"i":{"c":{}}}}}}}},"j":{"a":{"n":{"c":{"i":{"s":{}}}},"m":{"e":{"s":{}}}}},"e":{"v":{"e":{"n":{}}},"x":{"h":{"i":{"b":{"i":{"t":{"i":{"n":{"g":{}}}}}}}}},"a":{"s":{"y":{"g":{"o":{"i":{"n":{"g":{}}}}}}}}},"r":{"o":{"u":{"n":{"d":{"e":{"d":{}}}}}},"e":{"a":{"l":{"l":{"y":{}}}},"d":{}},"i":{"p":{"e":{}}},"a":{"c":{"y":{}},"s":{"t":{"e":{"a":{"u":{"s":{}}}}}}}},"m":{"o":{"r":{"e":{}},"u":{"t":{"h":{"f":{"i":{"l":{"l":{"i":{"n":{"g":{}}}}}}}}}}},"e":{"d":{"i":{"u":{"m":{"b":{"o":{"d":{"i":{"e":{"d":{}}}}}}}}}}},"i":{"c":{"h":{"e":{"l":{}}}}},"a":{"d":{"e":{}},"i":{"s":{"o":{"n":{}}}}},"y":{}},"d":{"e":{"c":{"e":{"p":{"t":{"i":{"v":{"e":{"l":{"y":{}}}}}}}}},"e":{"p":{}},"s":{"p":{"i":{"t":{"e":{}}}}}},"a":{"r":{"k":{}}}},"l":{"o":{"o":{"k":{"i":{"n":{"g":{}}}}}},"i":{"k":{"e":{}},"g":{"h":{"t":{"l":{"y":{}}}}}},"u":{"s":{"h":{"l":{"y":{}}}}},"a":{"u":{"r":{"e":{"n":{"c":{"e":{}}}}}}}},"s":{"u":{"p":{"e":{"r":{"b":{},"r":{"i":{"p":{"e":{}}}},"d":{"e":{"n":{"s":{"e":{}}}}}}}},"c":{"c":{"u":{"l":{"e":{"n":{"t":{}}}}}}}},"h":{"o":{"w":{"s":{}}}},"i":{"l":{"k":{"y":{}},"v":{"e":{"r":{}}}},"t":{"u":{"a":{"t":{"e":{"d":{}}}}}}},"w":{"e":{"e":{"t":{"t":{"h":{"e":{}}}}}}},"p":{"o":{"r":{"t":{"i":{"n":{"g":{}}}}}}},"o":{"m":{"e":{}}},"t":{"i":{"l":{"l":{}}},"y":{"l":{"e":{}}}},"a":{"t":{"u":{"r":{"a":{"t":{"e":{"d":{}}}}}}}}},"w":{"i":{"n":{"e":{}}},"h":{"a":{"t":{}}}},"b":{"o":{"t":{"h":{}}},"r":{"o":{"a":{"d":{}}},"i":{"g":{"h":{"t":{}}}}},"e":{"a":{"u":{"c":{"a":{"s":{"t":{"e":{"l":{}}}}}}}}}},"p":{"u":{"r":{"e":{}}},"l":{"u":{"s":{"h":{}}}},"e":{"r":{"h":{"a":{"p":{"s":{}}}},"r":{"i":{"n":{}}}}},"r":{"e":{"v":{"i":{"o":{"u":{"s":{"l":{"y":{}}}}}}}}}},"y":{"o":{"u":{"t":{"h":{"f":{"u":{"l":{}}}}},"l":{"l":{}}}}},"c":{"o":{"m":{"p":{"o":{"s":{"e":{"d":{}}}}}},"n":{"s":{"e":{"r":{"v":{"a":{"t":{"i":{"v":{"e":{"l":{"y":{}}}}}}}}}}}}},"r":{"u":{"s":{"h":{"e":{"d":{}}}}},"e":{"a":{"m":{"y":{}}}}},"l":{"a":{"i":{"r":{"e":{"t":{"t":{"e":{}}}}}}}}},"o":{"f":{"f":{"e":{"r":{"s":{}}}}},"n":{"e":{}},"p":{"a":{"q":{"u":{"e":{}}}}}},"i":{"n":{"t":{"e":{"r":{"e":{"s":{"t":{"i":{"n":{"g":{}}}}}}}}}}}},"a":{}},"d":{"a":{"n":{"i":{"e":{"n":{"n":{"e":{"s":{}}}}},"a":{}}}}}},"u":{"b":{"a":{"r":{"b":{"l":{"i":{"k":{"e":{}}}}}}}}},"i":{"n":{"e":{"g":{"a":{"u":{}}}},"o":{"f":{"i":{"e":{"l":{"d":{"s":{}}}}}}}}},"e":{"i":{"n":{"g":{"a":{"u":{}},"r":{"a":{"f":{"e":{"n":{"b":{"e":{"r":{"g":{}}}}}}}}}},"h":{"e":{"s":{"s":{"e":{"n":{}}}}}},"b":{"e":{"r":{"g":{}}}}}}},"a":{"m":{}},"y":{"s":{},"t":{"h":{"m":{}}}}},"u":{"b":{"y":{"p":{"u":{"r":{"p":{"l":{"e":{"t":{"i":{"n":{"g":{"e":{"d":{}}}}}},"h":{"u":{"e":{"d":{}}}},"c":{"o":{"l":{"o":{"r":{"e":{"d":{}}}}}}},"p":{"l":{"u":{"m":{"c":{"o":{"l":{"o":{"r":{"e":{"d":{}}}}}}}}}}}}}}}},"l":{"u":{"m":{"c":{"o":{"l":{"o":{"r":{"e":{"d":{}}}}}}},"p":{"u":{"r":{"p":{"l":{"e":{}}}}}}}}}},"c":{"o":{"l":{"o":{"r":{"e":{"d":{}}},"u":{"r":{"e":{"d":{}}}}}}}},"g":{"a":{"r":{"n":{"e":{"t":{"c":{"o":{"l":{"o":{"r":{"e":{"d":{}}}}}}}}}}}}},"r":{"e":{"d":{}}},"h":{"u":{"e":{"d":{}}}},"s":{"t":{"y":{"l":{"e":{}}}}},"v":{"i":{"o":{"l":{"e":{"t":{}}}}}},"b":{"l":{"a":{"c":{"k":{}}}}}},"e":{"n":{"s":{},"o":{}},"s":{"c":{"o":{}}}},"i":{"c":{"o":{"n":{}}},"o":{"s":{}},"n":{"o":{"r":{"o":{}}},"t":{"h":{"i":{"s":{}}}},"e":{"l":{"l":{"i":{}}}}},"z":{"z":{"o":{}}}},"b":{"e":{"r":{"y":{}}}},"r":{"a":{}},"n":{},"a":{"n":{}}},"s":{"t":{"i":{"c":{"i":{"t":{"y":{}}},"o":{},"h":{"e":{"w":{"e":{"d":{}}}}}}},"e":{"n":{"b":{"e":{"r":{"g":{}}}}}},"y":{},"m":{"a":{"n":{"n":{}}}}},"s":{"i":{"a":{"n":{}},"s":{}},"e":{"l":{"l":{}},"t":{}},"o":{}},"h":{"i":{"n":{"g":{}}},"e":{"s":{}}},"d":{"e":{"n":{}}}},"t":{"h":{"e":{"r":{"f":{"o":{"r":{"d":{}}}},"g":{"l":{"e":{"n":{}}}}}}}},"c":{"h":{"o":{"t":{"s":{},"t":{"e":{"s":{}}}}},"e":{"t":{"a":{"s":{"t":{"i":{"n":{"g":{}}}}}},"s":{}},"w":{"a":{"l":{"t":{"e":{"r":{}}}}}}}},"a":{},"o":{"n":{"i":{"a":{}}}}},"l":{"l":{"y":{}},"e":{"s":{"t":{"r":{"a":{"n":{"s":{"l":{"a":{"t":{"e":{"d":{}}}}}}}}}}},"b":{"e":{"n":{"d":{"i":{"n":{"g":{}}}}}}}},"o":{}},"f":{"i":{"n":{"a":{"g":{"o":{"o":{"d":{}}}},"s":{},"m":{"e":{"d":{"i":{"u":{"m":{"b":{"o":{"d":{"i":{"e":{"d":{}}}}}}}}}}}}}}},"f":{"i":{"n":{"o":{},"a":{}}}},"u":{"s":{}}},"g":{"g":{"e":{"d":{},"r":{"i":{}}}},"i":{"e":{"n":{"s":{}}}}},"h":{"l":{"m":{"a":{"n":{"n":{}}}}}},"n":{"n":{"i":{"n":{"g":{}}},"e":{"r":{}}},"s":{},"q":{"u":{"i":{"s":{"t":{"s":{}}}}}},"i":{"s":{}},"c":{"a":{"r":{"i":{"s":{}}}},"o":{"t":{"f":{"u":{"l":{"l":{"b":{"o":{"d":{"i":{"e":{"d":{}}}}}}}}}}}}},"d":{"o":{"w":{"n":{}}}},"r":{"i":{"g":{}}}},"p":{"p":{"e":{"r":{"t":{"s":{"b":{"e":{"r":{"g":{"e":{"r":{}}}}}}}}}},"i":{}},"e":{"r":{"t":{}}}},"e":{"d":{"a":{}},"t":{}},"d":{"o":{"l":{"p":{"h":{}},"f":{}}},"e":{"s":{"h":{"e":{"i":{"m":{"e":{"r":{"o":{"f":{"f":{"d":{"r":{"y":{}}}}}}}}}}}}},"r":{"a":{}}},"m":{"a":{"n":{}}},"y":{},"i":{"n":{"i":{}},"s":{"b":{"o":{"u":{"r":{"g":{}}}}}}},"d":{}},"m":{"p":{"f":{}},"b":{"l":{"e":{}}},"e":{"n":{}}},"w":{"e":{"r":{}}},"a":{"u":{"x":{}}},"i":{"n":{"a":{"r":{"t":{}}},"s":{}},"t":{"e":{"n":{}}}},"j":{"a":{}},"v":{"e":{"i":{}}},"r":{"a":{"l":{}}}},"j":{"v":{"i":{"e":{"d":{"o":{"s":{}}}},"n":{"e":{"d":{"o":{"s":{"w":{"h":{"e":{"n":{}}}}}}}}}}},"o":{"n":{"w":{"i":{"n":{"e":{"c":{"o":{"m":{}}}}}}}}}},"c":{"o":{"l":{"t":{"a":{"n":{"t":{"m":{"a":{"n":{"i":{"p":{"u":{"l":{"a":{"n":{"t":{}}}}}}}}}}}}},"s":{}}}}},"s":{"e":{"r":{"v":{"e":{}}}},"u":{"r":{"g":{"e":{"n":{"c":{"e":{}}}}}}}},"t":{"i":{"e":{}},"e":{"b":{"o":{"e":{"u":{"f":{}}}}}},"t":{"g":{"e":{"n":{}}}}},"f":{"i":{"n":{"a":{}}},"o":{"l":{"s":{}}}},"p":{"s":{"f":{"i":{"n":{"a":{"a":{}}}}}}},"g":{"i":{"o":{"n":{"a":{"l":{}}}},"a":{},"s":{},"n":{"e":{}}},"a":{"l":{}},"n":{"i":{}}},"y":{"a":{"n":{}},"e":{"b":{"e":{"n":{}}},"t":{"h":{"i":{"s":{}}}}},"j":{"e":{"n":{"k":{"o":{"v":{}}}}}}},"k":{"a":{"t":{"s":{"i":{"t":{"e":{"l":{"i":{}}}}}}}}},"z":{"i":{"g":{"e":{"r":{}}}}},"b":{"l":{"e":{"s":{}}}},"d":{"e":{"s":{"h":{"e":{"i":{"m":{"e":{"r":{}}}}}}}}},"m":{"o":{"n":{"d":{"e":{"t":{}}}}},"u":{"a":{"g":{"e":{}}}},"i":{"g":{"b":{"e":{"r":{"g":{}}}}}}},"v":{"e":{"s":{}},"a":{"y":{}}},"n":{"c":{"o":{"t":{}}}}}}